[
    {
    "id" : "diagnostico",
    "etiqueta" : "Diagnótico",
     "accion": [
                        {
                            "id" : "planFebrero",
                            "etiqueta" : "Plan de Febrero"
                        },
                        {
                            "id" : "planMarzo",
                            "etiqueta" : "Plan de Marzo"
                        }                                                    
                      ] 
    },
    {
        "id" : "concienciaCorporal",
        "etiqueta" : "Conciencia corporal",
         "accion": [
                            {
                                "id" : "discriminacion",
                                "etiqueta" : "Discriminación"
                            },
                            {
                                "id" : "identificacion",
                                "etiqueta" : "Identificación"
                            },                                                    ,
                            {
                                "id" : "reconocimiento",
                                "etiqueta" : "Reconocimiento"
                            },
                            {
                                "id" : "desarrollo",
                                "etiqueta" : "Desarrollo"
                            }
                          ] 
    },
    {
        "id" : "imagenCorporal",
        "etiqueta" : "Imagen corporal",
        "accion": [
                                {
                                    "id" : "identificacion",
                                    "etiqueta" : "Identificación"
                                },
                                {
                                    "id" : "recnonocimiento",
                                    "etiqueta" : "Reconocimiento"
                                },
                                {
                                    "id" : "demostracion",
                                    "etiqueta" : "Demostración"
                                }
                              ] 
    },
    {
        "id" : "IdentidadSexual",
        "etiqueta" : "Identidad sexual",
        "accion": [
                                {
                                    "id" : "descripcion",
                                    "etiqueta" : "Descripción"
                                },
                                {
                                    "id" : "reconocimiento",
                                    "etiqueta" : "Reconocimiento"
                                },
                                {
                                    "id" : "comprension",
                                    "etiqueta" : "Comprension"
                                }
                              ] 
    },
    {
        "id" : "posibilidadesAccion",
        "etiqueta" : "Posibilidades de acción",
        "accion": [
                                {
                                    "id" : "planFebrero",
                                    "etiqueta" : "Plan de Febrero"
                                },
                                {
                                    "id" : "planMarzo",
                                    "etiqueta" : "Plan de Marzo"
                                }                                                    
                              ] 
    }

    

]